spindrift/__init__.py
spindrift/cli.py
spindrift/compat.py
spindrift/packager.py
spindrift/wsgi.py
spindrift-5.6.data/scripts/spindrift
spindrift-5.6.dist-info/licenses/LICENSE
spindrift-5.6.dist-info/METADATA
spindrift-5.6.dist-info/WHEEL
spindrift-5.6.dist-info/top_level.txt
spindrift-5.6.dist-info/RECORD
