Metadata-Version: 2.4
Name: spindrift
Version: 5.6
Summary: package python applications for AWS Lambda, AWS Elastic Beanstalk, AWS Batch (Docker)
Home-page: https://github.com/f0rk/spindrift
Author: Ryan P. Kelly
Author-email: ryan@ryankelly.us
Classifier: Development Status :: 5 - Production/Stable
Classifier: Environment :: Console
Classifier: Framework :: Flask
Classifier: Intended Audience :: Developers
Classifier: Intended Audience :: System Administrators
Classifier: License :: OSI Approved :: MIT License
Classifier: Operating System :: MacOS :: MacOS X
Classifier: Operating System :: POSIX
Classifier: Programming Language :: Python :: 2.7
Classifier: Programming Language :: Python :: 3
Classifier: Topic :: Internet :: WWW/HTTP :: WSGI
Classifier: Topic :: Software Development :: Build Tools
Classifier: Topic :: Software Development :: Libraries
License-File: LICENSE
Requires-Dist: pip
Requires-Dist: pyyaml
Requires-Dist: requests
Requires-Dist: werkzeug
Dynamic: author
Dynamic: author-email
Dynamic: classifier
Dynamic: home-page
Dynamic: license-file
Dynamic: requires-dist
Dynamic: summary
